setup.py
./tinys3/__init__.py
./tinys3/auth.py
./tinys3/connection.py
./tinys3/multipart_upload.py
./tinys3/pool.py
./tinys3/request_factory.py
./tinys3/util.py
tinys3.egg-info/PKG-INFO
tinys3.egg-info/SOURCES.txt
tinys3.egg-info/dependency_links.txt
tinys3.egg-info/pbr.json
tinys3.egg-info/requires.txt
tinys3.egg-info/top_level.txt